__pyversor__.cpython-36m-x86_64-linux-gnu.so
pyversor/__init__.py
pyversor/cga/__init__.py
pyversor/ega/__init__.py
pyversor/ega/generate/__init__.py
pyversor/visuals/__init__.py
pyversor/visuals/gui.py
pyversor-0.0.1.dist-info/DESCRIPTION.rst
pyversor-0.0.1.dist-info/METADATA
pyversor-0.0.1.dist-info/RECORD
pyversor-0.0.1.dist-info/WHEEL
pyversor-0.0.1.dist-info/metadata.json
pyversor-0.0.1.dist-info/top_level.txt
