Metadata-Version: 2.0
Name: pyversor
Version: 0.0.1
Summary: Python bindings for the Versor Geometric Algebra
Home-page: UNKNOWN
Author: Lars Tingelstad
Author-email: lars.tingelstad@ntnu.no
License: UNKNOWN
Platform: UNKNOWN
